{
    "name": "09_Envio_JSON_HTTP",
    "nodes": [
        {
            "parameters": {
                "path": "send-json",
                "responseMode": "lastNode",
                "options": {}
            },
            "type": "n8n-nodes-base.webhook",
            "typeVersion": 1,
            "position": [
                0,
                0
            ],
            "id": "webhook-trigger",
            "name": "Webhook"
        },
        {
            "parameters": {
                "method": "POST",
                "url": "https://api.example.com/endpoint",
                "sendBody": true,
                "contentType": "json",
                "bodyParameters": {
                    "parameters": [
                        {
                            "name": "data",
                            "value": "={{$json}}"
                        }
                    ]
                },
                "options": {}
            },
            "type": "n8n-nodes-base.httpRequest",
            "typeVersion": 1,
            "position": [
                200,
                0
            ],
            "id": "http-post",
            "name": "HTTP Request"
        }
    ],
    "connections": {
        "Webhook": {
            "main": [
                [
                    {
                        "node": "HTTP Request",
                        "type": "main",
                        "index": 0
                    }
                ]
            ]
        }
    }
}